ai_review_assistant/__init__.py
ai_review_assistant/main.py
ai_review_assistant/review.py
ai_review_assistant/hooks/__init__.py
ai_review_assistant/hooks/pre_commit.py
ai_review_assistant-0.7.0.post0.dist-info/METADATA
ai_review_assistant-0.7.0.post0.dist-info/WHEEL
ai_review_assistant-0.7.0.post0.dist-info/entry_points.txt
ai_review_assistant-0.7.0.post0.dist-info/top_level.txt
ai_review_assistant-0.7.0.post0.dist-info/RECORD
