Metadata-Version: 2.1
Name: ai_review_assistant
Version: 0.7.0.post0
Summary: An AI-powered code review assistant
Home-page: https://github.com/vandriichuk/ai_review_assistant
Author: Viktor Andriichuk
Author-email: v.andriichuk@gmail.com
Classifier: Development Status :: 3 - Alpha
Classifier: Intended Audience :: Developers
Classifier: License :: OSI Approved :: MIT License
Classifier: Programming Language :: Python :: 3.11
Requires-Python: >=3.11
Requires-Dist: anthropic >=0.31.2
Requires-Dist: click >=8.1.7
Requires-Dist: gitpython >=3.1.43
Requires-Dist: langchain >=0.2.11
Requires-Dist: langchain-core >=0.2.23
Requires-Dist: langchain-openai >=0.1.17
Requires-Dist: langchain-anthropic >=0.1.20
Requires-Dist: openai >=1.37.0
Requires-Dist: rich >=13.0.0
Requires-Dist: toml >=0.10.2
Requires-Dist: types-toml >=0.10.8
Requires-Dist: importlib-metadata ; python_version < "3.8"
Provides-Extra: dev
Requires-Dist: pytest >=7.0.0 ; extra == 'dev'
Requires-Dist: pylint >=2.15.0 ; extra == 'dev'
Requires-Dist: black >=22.0.0 ; extra == 'dev'
